[
  {
    "name": "ネコパンツ",
    "description": "極寒の地でも最高のパフォーマンスを\n発揮できる防寒対策を施した遠距離型キャラ\nキモネコの進化系お遊びキャラクター",
    "image": "https://img.game8.jp/1673890/cbdba3b5ac4a2be05f7f7879871c10ca.jpeg/show",
    "health": 1000,
    "attack": 250,
    "dps": 60,
    "range": 1,
    "kb": 3,
    "speed": 10,
    "reach": 350,
    "cost": 525,
    "frequency": 125,
    "animation": 6,
    "again": 76,
    "ability": [],
    "attribute": [],
    "rarity": 2,
    "collaboration": false
  },
  {
    "name": "ネコ葉っぱ",
    "description": "急所の防御に特化した遠距離キャラ\nただし戦闘には、まったく役立っていない\nキモネコの進化系お遊びキャラクター",
    "image": "https://img.game8.jp/1673902/69ad3580f12a8c438efc64026b4c2543.jpeg/show",
    "health": 1000,
    "attack": 250,
    "dps": 60,
    "range": 1,
    "kb": 3,
    "speed": 10,
    "reach": 350,
    "cost": 525,
    "frequency": 125,
    "animation": 6,
    "again": 76,
    "ability": [],
    "attribute": [],
    "rarity": 2,
    "collaboration": false
  },
  {
    "name": "ネコぺろきゃん",
    "description": "防御することを諦めていた遠距離キャラだが\n親切なネコのおかげで、もう大丈夫\n範囲攻撃を取得",
    "image": "https://img.game8.jp/1699961/0ffc412b6f48bb0cee17f48c4de70e2d.jpeg/show",
    "health": 1000,
    "attack": 250,
    "dps": 60,
    "range": 2,
    "kb": 3,
    "speed": 10,
    "reach": 350,
    "cost": 525,
    "frequency": 125,
    "animation": 6,
    "again": 76,
    "ability": [],
    "attribute": [],
    "rarity": 2,
    "collaboration": false
  }
]
